xpublish_tiles/__init__.py
xpublish_tiles/_version.py
xpublish_tiles/config.py
xpublish_tiles/grids.py
xpublish_tiles/lib.py
xpublish_tiles/logger.py
xpublish_tiles/pipeline.py
xpublish_tiles/py.typed
xpublish_tiles/tiles_lib.py
xpublish_tiles/types.py
xpublish_tiles/utils.py
xpublish_tiles/validators.py
xpublish_tiles/cli/__init__.py
xpublish_tiles/cli/bench.py
xpublish_tiles/cli/benchmark_common.py
xpublish_tiles/cli/main.py
xpublish_tiles/cli/titiler_bench.py
xpublish_tiles/render/__init__.py
xpublish_tiles/render/quiver.py
xpublish_tiles/render/raster.py
xpublish_tiles/testing/__init__.py
xpublish_tiles/testing/datasets.py
xpublish_tiles/testing/lib.py
xpublish_tiles/testing/tiles.py
xpublish_tiles/testing/grids/extract_n320.py
xpublish_tiles/testing/grids/n320_grid.csv
xpublish_tiles/xpublish/tiles/__init__.py
xpublish_tiles/xpublish/tiles/metadata.py
xpublish_tiles/xpublish/tiles/plugin.py
xpublish_tiles/xpublish/tiles/tile_matrix.py
xpublish_tiles/xpublish/tiles/types.py
xpublish_tiles/xpublish/wms/__init__.py
xpublish_tiles/xpublish/wms/plugin.py
xpublish_tiles/xpublish/wms/types.py
xpublish_tiles/xpublish/wms/utils.py
xpublish_tiles-0.3.12.dist-info/METADATA
xpublish_tiles-0.3.12.dist-info/WHEEL
xpublish_tiles-0.3.12.dist-info/entry_points.txt
xpublish_tiles-0.3.12.dist-info/licenses/LICENSE
xpublish_tiles-0.3.12.dist-info/RECORD
