Metadata-Version: 2.4
Name: xpublish-tiles
Version: 0.3.12
Summary: Tiles router for xpublish
Project-URL: Homepage, https://github.com/earth-mover/xpublish-tiles
Project-URL: Repository, https://github.com/earth-mover/xpublish-tiles
Author-email: Matthew Iannucci <matt@earthmover.io>, Deepak Cherian <deepak@earthmover.io>, Tom Nicholas <tom@earthmover.io>
License: Apache-2.0
License-File: LICENSE
Classifier: License :: OSI Approved :: Apache Software License
Requires-Python: >=3.11
Requires-Dist: aiohttp>=3.12.15
Requires-Dist: cachetools>=5.5.2
Requires-Dist: cf-xarray>=0.10.8
Requires-Dist: cftime>=1.6.4.post1
Requires-Dist: datashader>=0.18.2
Requires-Dist: donfig>=0.8.0
Requires-Dist: fastapi
Requires-Dist: matplotlib>=3.10.5
Requires-Dist: morecantile>=5.4.2
Requires-Dist: numba-celltree>=0.4.1
Requires-Dist: numba>=0.60.0
Requires-Dist: numbagg>=0.9.0
Requires-Dist: pillow>=11.3.0
Requires-Dist: pydantic-xml>=2.17.3
Requires-Dist: pyproj>=3.7.1
Requires-Dist: rasterix>=0.1a4
Requires-Dist: requests>=2.32.5
Requires-Dist: structlog>=24.4.0
Requires-Dist: tbb>=2022.2.0; sys_platform == 'linux'
Requires-Dist: toolz>=1.0.0
Requires-Dist: triangle>=20250106
Requires-Dist: xarray>=2025.08.0
Requires-Dist: xpublish>=0.3.0
Requires-Dist: zarr>=3.1.2
Provides-Extra: testing
Requires-Dist: hypothesis>=6.136.6; extra == 'testing'
Requires-Dist: pytest-asyncio>=1.1.0; extra == 'testing'
Requires-Dist: pytest-cov>=6.2.1; extra == 'testing'
Requires-Dist: pytest-randomly>=3.16.0; extra == 'testing'
Requires-Dist: pytest-xdist>=3.6.1; extra == 'testing'
Requires-Dist: pytest>=8.4.1; extra == 'testing'
Requires-Dist: scikit-image>=0.25.2; extra == 'testing'
Requires-Dist: syrupy>=4.9.1; extra == 'testing'
Requires-Dist: titiler>=0.24.0; extra == 'testing'
